{
  "app:go-back": [
    {
      "modifiers": [
        "Mod",
        "Alt"
      ],
      "key": "ArrowLeft"
    },
    {
      "modifiers": [
        "Alt",
        "Mod"
      ],
      "key": "H"
    }
  ],
  "app:go-forward": [
    {
      "modifiers": [
        "Mod",
        "Alt"
      ],
      "key": "ArrowRight"
    },
    {
      "modifiers": [
        "Alt",
        "Mod"
      ],
      "key": "L"
    }
  ],
  "window:zoom-out": [
    {
      "modifiers": [
        "Mod"
      ],
      "key": "-"
    }
  ],
  "window:zoom-in": [
    {
      "modifiers": [
        "Mod"
      ],
      "key": "+"
    }
  ],
  "templater-obsidian:lolö.md": [
    {
      "modifiers": [
        "Alt",
        "Mod"
      ],
      "key": "I"
    }
  ],
  "app:delete-file": [
    {
      "modifiers": [
        "Alt"
      ],
      "key": "Delete"
    }
  ],
  "obsidian-git:push": [
    {
      "modifiers": [
        "Mod",
        "Shift"
      ],
      "key": "B"
    }
  ]
}